src/polite_lib/__init__.py
src/polite_lib/file_tools/__init__.py
src/polite_lib/file_tools/backblaze.py
src/polite_lib/file_tools/file_tools.py
src/polite_lib/file_tools/minio.py
src/polite_lib/fmt/__init__.py
src/polite_lib/fmt/fmt_html.py
src/polite_lib/fmt/fmt_nums.py
src/polite_lib/fmt/fmt_rich.py
src/polite_lib/notify/__init__.py
src/polite_lib/notify/quigley_notify.py
src/polite_lib/utils/__init__.py
src/polite_lib/utils/convert.py
src/polite_lib/utils/date_utils.py
src/polite_lib/utils/dict_tools.py
src/polite_lib/utils/dyn_import.py
src/polite_lib/utils/mathy.py
src/polite_lib/utils/network_tools.py
src/polite_lib/utils/url_tools.py
src/polite_lib/utils/xlate.py
src/polite_lib/version.py
polite_lib-0.0.9.7.dist-info/METADATA
polite_lib-0.0.9.7.dist-info/WHEEL
polite_lib-0.0.9.7.dist-info/RECORD
